dictionary/__init__.py
dictionary/dictionary.py
king_dictionary-2.2.9.dist-info/METADATA
king_dictionary-2.2.9.dist-info/WHEEL
king_dictionary-2.2.9.dist-info/top_level.txt
king_dictionary-2.2.9.dist-info/RECORD
